edp/redy/__init__.py
edp/redy/app.py
edp/redy/cli/__init__.py
edp/redy/cli/argparser.py
edp/redy/cli/cli.py
edp/redy/services/__init__.py
edp/redy/services/api.py
edp/redy/services/auth.py
edp/redy/services/stream.py
edp/redy/services/wsmqtt.py
edp/redy/services/devices/__init__.py
edp/redy/services/devices/constants.py
edp/redy/services/devices/service.py
edp/redy/services/devices/models/__init__.py
edp/redy/services/devices/models/devicemodel.py
edp/redy/services/devices/models/modulesmodel.py
edp/redy/services/energy/__init__.py
edp/redy/services/energy/constants.py
edp/redy/services/energy/service.py
edp/redy/services/energy/models/predictionmodel.py
edp/redy/services/houses/__init__.py
edp/redy/services/houses/constants.py
edp/redy/services/houses/service.py
edp/redy/services/houses/models/__init__.py
edp/redy/services/houses/models/contractedpowermodel.py
edp/redy/services/houses/models/housemodel.py
edp/redy/services/houses/models/tariffmodel.py
edp/redy/services/statevars/__init__.py
edp/redy/services/statevars/constants.py
edp/redy/services/statevars/service.py
edp/redy/services/statevars/models/__init__.py
edp/redy/services/statevars/models/statevarsmodel.py
edp_redy_api-1.1.2.dist-info/LICENSE
edp_redy_api-1.1.2.dist-info/METADATA
edp_redy_api-1.1.2.dist-info/WHEEL
edp_redy_api-1.1.2.dist-info/entry_points.txt
edp_redy_api-1.1.2.dist-info/top_level.txt
edp_redy_api-1.1.2.dist-info/RECORD
