Metadata-Version: 2.1
Name: edp-redy-api
Version: 1.1.2
Summary: EDP Redy API
Author-email: Hugo Gomes <hgomes88@gmail.com>
Project-URL: Homepage, https://github.com/hgomes88/edp-redy
Project-URL: Repository, https://github.com/hgomes88/edp-redy.git
Project-URL: Tracker, https://github.com/hgomes88/edp-redy/issues
Project-URL: Download, https://pypi.org/project/edp-redy/
Classifier: Programming Language :: Python :: 3
Classifier: License :: OSI Approved :: Apache Software License
Classifier: Operating System :: OS Independent
Requires-Python: >=3.8
License-File: LICENSE
Requires-Dist: urllib3 <1.27,>=1.25.4
Requires-Dist: aiohttp ==3.8.6
Requires-Dist: awscrt ==0.19.1
Requires-Dist: awsiotsdk ==1.19.0
Requires-Dist: boto3 ==1.28.83
Requires-Dist: boto3-stubs[cognito-identity] ==1.28.83
Requires-Dist: dataclasses-json ==0.6.2
Requires-Dist: warrant ==0.4.0
Requires-Dist: aiocron ==1.8
Provides-Extra: dev
Requires-Dist: build ==1.0.3 ; extra == 'dev'
Requires-Dist: pytest ==7.4.3 ; extra == 'dev'
Requires-Dist: pytest-asyncio ==0.21.1 ; extra == 'dev'
Requires-Dist: pre-commit ==3.5.0 ; extra == 'dev'
Requires-Dist: types-python-dateutil ==2.8.19.14 ; extra == 'dev'
Requires-Dist: ruff ~=0.1.5 ; extra == 'dev'
